malaya/__init__.py
malaya/cluster.py
malaya/constituency.py
malaya/dependency.py
malaya/embedding.py
malaya/emotion.py
malaya/entity.py
malaya/jawi.py
malaya/knowledge_graph.py
malaya/language_detection.py
malaya/language_model.py
malaya/normalize.py
malaya/nsfw.py
malaya/num2word.py
malaya/paraphrase.py
malaya/pos.py
malaya/preprocessing.py
malaya/reranker.py
malaya/segmentation.py
malaya/sentiment.py
malaya/stack.py
malaya/stem.py
malaya/syllable.py
malaya/tatabahasa.py
malaya/tokenizer.py
malaya/transformer.py
malaya/translation.py
malaya/true_case.py
malaya/word2num.py
malaya/wordvector.py
malaya/augmentation/__init__.py
malaya/augmentation/abstractive.py
malaya/augmentation/base.py
malaya/augmentation/rules.py
malaya/dictionary/__init__.py
malaya/dictionary/bahasa/__init__.py
malaya/dictionary/bahasa/adun.py
malaya/dictionary/bahasa/binatang.py
malaya/dictionary/bahasa/cambridge_words.py
malaya/dictionary/bahasa/city.py
malaya/dictionary/bahasa/country.py
malaya/dictionary/bahasa/daerah.py
malaya/dictionary/bahasa/dbp.py
malaya/dictionary/bahasa/kamus_dewan.py
malaya/dictionary/bahasa/negeri.py
malaya/dictionary/bahasa/parlimen.py
malaya/dictionary/bahasa/place.py
malaya/dictionary/bahasa/places.py
malaya/dictionary/bahasa/words.py
malaya/dictionary/english/__init__.py
malaya/dictionary/english/words.py
malaya/dictionary/mandarin/__init__.py
malaya/dictionary/mandarin/pinyin.py
malaya/function/__init__.py
malaya/function/activation.py
malaya/function/parse_dependency.py
malaya/function/validator.py
malaya/function/constituency/__init__.py
malaya/function/constituency/chart_helper.py
malaya/function/constituency/evaluate.py
malaya/function/constituency/trees_newline.py
malaya/generator/__init__.py
malaya/generator/isi_penting.py
malaya/graph/__init__.py
malaya/graph/fast_pagerank.py
malaya/graph/pagerank.py
malaya/graph/triplet.py
malaya/keyword/__init__.py
malaya/keyword/abstractive.py
malaya/keyword/extractive.py
malaya/model/__init__.py
malaya-5.1.dist-info/LICENSE
malaya-5.1.dist-info/METADATA
malaya-5.1.dist-info/WHEEL
malaya-5.1.dist-info/top_level.txt
malaya-5.1.dist-info/RECORD
