Metadata-Version: 2.1
Name: malaya
Version: 5.1
Summary: Natural-Language-Toolkit for bahasa Malaysia, powered by Tensorflow and PyTorch.
Home-page: https://github.com/huseinzol05/Malaya
Download-URL: https://github.com/huseinzol05/Malaya/archive/master.zip
Author: huseinzol05
Author-email: husein.zol05@gmail.com
License: MIT
Keywords: nlp,bm
Classifier: Programming Language :: Python :: 3.6
Classifier: Intended Audience :: Developers
Classifier: License :: OSI Approved :: MIT License
Classifier: Operating System :: OS Independent
Classifier: Topic :: Text Processing
Requires-Python: >=3.6
License-File: LICENSE
Requires-Dist: dateparser
Requires-Dist: scikit-learn (>=1.2)
Requires-Dist: requests
Requires-Dist: unidecode
Requires-Dist: numpy
Requires-Dist: scipy
Requires-Dist: ftfy
Requires-Dist: networkx
Requires-Dist: sentencepiece
Requires-Dist: tqdm
Requires-Dist: malaya-boilerplate (>=0.0.25)
Requires-Dist: regex
Requires-Dist: transformers
